{"cameraMode":{"drawMode":0,"name":"Shaded","section":"Shading Mode"},"sceneLighting":true,"audioPlay":false,"sceneViewState":{"m_AlwaysRefresh":false,"showFog":true,"showSkybox":true,"showFlares":true,"showImageEffects":true,"showParticleSystems":true,"showVisualEffectGraphs":true,"m_FxEnabled":true},"in2DMode":false,"pivot":{"x":-0.1311490386724472,"y":4.091885566711426,"z":-5.369548797607422},"rotation":{"x":0.03345884382724762,"y":-0.1497025340795517,"z":-0.002438739174976945,"w":0.9891512989997864},"size":0.07781831175088883,"orthographic":false}